llama_index/vector_stores/objectbox/__init__.py
llama_index/vector_stores/objectbox/base.py
llama_index_vector_stores_objectbox-0.1.0a0.dist-info/METADATA
llama_index_vector_stores_objectbox-0.1.0a0.dist-info/WHEEL
llama_index_vector_stores_objectbox-0.1.0a0.dist-info/RECORD
