Metadata-Version: 2.1
Name: llama-index-vector-stores-objectbox
Version: 0.1.0a0
Summary: Integration package connecting ObjectBox and LlamaIndex
License: MIT
Author: ObjectBox
Requires-Python: >=3.8.1,<4.0
Classifier: Development Status :: 4 - Beta
Classifier: License :: OSI Approved :: MIT License
Classifier: Programming Language :: Python :: 3
Classifier: Programming Language :: Python :: 3.9
Classifier: Programming Language :: Python :: 3.10
Classifier: Programming Language :: Python :: 3.11
Classifier: Programming Language :: Python :: 3.12
Requires-Dist: llama-index-core (>=0.11.0,<0.12.0)
Requires-Dist: objectbox (>=4.0.0,<5.0.0)
